__init__.py
keewee/__init__.py
keewee/keewee.py
keewee/monkey/__init__.py
keewee/monkey/monkey_patch.py
keewee/monkey/some_app.py
keewee-0.2.dist-info/LICENSE
keewee-0.2.dist-info/METADATA
keewee-0.2.dist-info/WHEEL
keewee-0.2.dist-info/top_level.txt
keewee-0.2.dist-info/RECORD
