Metadata-Version: 2.1
Name: keewee
Version: 0.2
Summary: Global application state management and recording
Author: Erik J Kostic
Project-URL: Homepage, https://github.com/eineruntervielen/keewee
Classifier: Development Status :: 4 - Beta
Classifier: Topic :: Software Development :: Libraries :: Python Modules
Classifier: Programming Language :: Python :: 3.10
Classifier: Operating System :: OS Independent
Requires-Python: >=3.7
License-File: LICENSE
